symmetr/__init__.py
symmetr/__main__.py
symmetr/conv_index.py
symmetr/find_eq.py
symmetr/fslib.py
symmetr/funcs_main.py
symmetr/groups.py
symmetr/input.py
symmetr/magndata.py
symmetr/mham.py
symmetr/noso.py
symmetr/noso_new.py
symmetr/rename.py
symmetr/symT.py
symmetr/symmetrize.py
symmetr/symmetrize_exp.py
symmetr/symmetry.py
symmetr/tensors.py
symmetr/test.py
symmetr/version.py
symmetr/findsym/data_magnetic.txt
symmetr/findsym/data_space.txt
symmetr/findsym/data_wyckoff.txt
symmetr/findsym/findsym
symmetr/findsym/findsym.txt
symmetr/findsym/mag_groups.txt
symmetr/findsym/syms_table.dat
symmetr/findsym/syms_table_hex.dat
symmetr/findsym/tables_wyckoff.txt
symmetr/hsnf/Z_module.py
symmetr/hsnf/__init__.py
symmetr/hsnf/__version__.py
symmetr/hsnf/integer_system.py
symmetr/hsnf/utils.py
symmetr-0.10.0.data/data/README_pypi.md
symmetr-0.10.0.data/scripts/symmetr
symmetr-0.10.0.dist-info/LICENSE
symmetr-0.10.0.dist-info/METADATA
symmetr-0.10.0.dist-info/WHEEL
symmetr-0.10.0.dist-info/top_level.txt
symmetr-0.10.0.dist-info/RECORD
