Metadata-Version: 2.1
Name: symmetr
Version: 0.10.0
Summary: Package for determining symmetry properties of crystals.
Home-page: https://bitbucket.org/zeleznyj/linear-response-symmetry
Author: Jakub Zelezny
Author-email: jakub.zelezny@gmail.com
License: UNKNOWN
Platform: UNKNOWN
Classifier: Programming Language :: Python :: 2.7
Classifier: Programming Language :: Python :: 3
Classifier: License :: OSI Approved :: Mozilla Public License 2.0 (MPL 2.0)
Classifier: Operating System :: POSIX :: Linux
Requires-Dist: future
Requires-Dist: six
Requires-Dist: numpy
Requires-Dist: sympy
Requires-Dist: prettytable
Requires-Dist: scipy
Requires-Dist: lxml
Requires-Dist: pandas
Requires-Dist: beautifulsoup4
Requires-Dist: pymatgen
Requires-Dist: numpy==1.16.4; python_version < "3"
Requires-Dist: numpy; python_version >= "3"
